simple_data_catalog_generator/__init__.py
simple_data_catalog_generator/add_figure_str.py
simple_data_catalog_generator/analysis_functions.py
simple_data_catalog_generator/create_adoc_table.py
simple_data_catalog_generator/create_catalog_page.py
simple_data_catalog_generator/create_concept_page.py
simple_data_catalog_generator/create_data_catalog.py
simple_data_catalog_generator/create_data_quality_table.py
simple_data_catalog_generator/create_dataservice_page.py
simple_data_catalog_generator/create_dataset_page.py
simple_data_catalog_generator/create_distribution_table.py
simple_data_catalog_generator/create_metadata_table.py
simple_data_catalog_generator/create_metric_page.py
simple_data_catalog_generator/create_policy_page.py
simple_data_catalog_generator/create_series_page.py
simple_data_catalog_generator/page_creation_functions.py
simple_data_catalog_generator/parse_catalog.py
simple_data_catalog_generator-0.0.2.dist-info/METADATA
simple_data_catalog_generator-0.0.2.dist-info/WHEEL
simple_data_catalog_generator-0.0.2.dist-info/licenses/LICENSE
simple_data_catalog_generator-0.0.2.dist-info/RECORD
