Metadata-Version: 2.4
Name: simple_data_catalog_generator
Version: 0.0.2
Summary: A simple package that supports data catalogging for small organizations and projects
Project-URL: Homepage, https://github.com/uuidea/simple_data_catalog
Project-URL: Issues, https://github.com/uuidea/simple_data_catalog/issues
Author-email: Joep van Genuchten <joep@uuidea.eu>
License-Expression: GPL-3.0-or-later
License-File: LICENSE
Classifier: Operating System :: OS Independent
Classifier: Programming Language :: Python :: 3
Requires-Python: >=3.8
Requires-Dist: asciidoc3
Requires-Dist: dataclasses
Requires-Dist: jinja2
Requires-Dist: linkml>=1.0
Requires-Dist: matplotlib
Requires-Dist: pandas
Requires-Dist: pydantic
Requires-Dist: pyyaml
Requires-Dist: rdflib
Requires-Dist: rich
Requires-Dist: validators
Requires-Dist: wordcloud
